{"data":[{"created_at":"2018-11-08T23:59:59.000Z","id":"1060683380893769728","referenced_tweets":[{"type":"retweeted","id":"1060645426854977536"}],"author_id":"33435305","entities":{"mentions":[{"start":3,"end":11,"username":"jonfavs","id":"130496027"}]},"text":"RT @jonfavs: Accusing people who want every vote counted of stealing an election is disgusting. \n\nMarco’s really gone full Trump here. http…"},{"created_at":"2018-11-08T23:59:58.000Z","id":"1060683376582025216","referenced_tweets":[{"type":"retweeted","id":"1060574566282493952"}],"author_id":"103643917","entities":{"mentions":[{"start":3,"end":10,"username":"McFaul","id":"454099919"}]},"text":"RT @McFaul: To those media outlets who covered extensively the \" the invading caravan\" before the election-- sometimes on page one -- but n…"},{"created_at":"2018-11-08T23:59:53.000Z","id":"1060683355769909248","referenced_tweets":[{"type":"retweeted","id":"1060645426854977536"}],"author_id":"20117737","entities":{"mentions":[{"start":3,"end":11,"username":"jonfavs","id":"130496027"}]},"text":"RT @jonfavs: Accusing people who want every vote counted of stealing an election is disgusting. \n\nMarco’s really gone full Trump here. http…"},{"created_at":"2018-11-08T23:59:53.000Z","id":"1060683354872442880","referenced_tweets":[{"type":"quoted","id":"1060678592017977344"}],"author_id":"266067803","text":"\uD83D\uDEA8ELECTION FRAUD ALERT!!\n\n#Trump #MAGA #VoterFraud #ElectionFraud #BrowardCounty #BrowardCountyElectionFraud https://t.co/Anjg1KdwlH"},{"created_at":"2018-11-08T23:59:52.000Z","id":"1060683352553017345","referenced_tweets":[{"type":"retweeted","id":"1060682018705543175"}],"author_id":"72854220","entities":{"mentions":[{"start":3,"end":15,"username":"annagalland","id":"7884802"}]},"text":"RT @annagalland: These photos are gorgeous. In the wake of a massive wave election that put a real check on Trump's power, they are another…"},{"created_at":"2018-11-08T23:59:52.000Z","id":"1060683352162926599","referenced_tweets":[{"type":"retweeted","id":"1060333386454175746"}],"author_id":"2731618972","entities":{"mentions":[{"start":3,"end":16,"username":"JohnQBarrett","id":"68194357"}]},"text":"RT @JohnQBarrett: Whittaker then was practicing law in his own law firm in Des Moines (Whitaker Hagenow &amp; Gustoff LLP).  On CNN, he was cri…"},{"created_at":"2018-11-08T23:59:49.000Z","id":"1060683341958135808","referenced_tweets":[{"type":"retweeted","id":"1060226413754793984"}],"author_id":"1895972022","entities":{"mentions":[{"start":3,"end":16,"username":"RealCandaceO","id":"878247600096509952"},{"start":55,"end":67,"username":"BarackObama","id":"813286"}]},"text":"RT @RealCandaceO: What I learned this election cycle:\n\n@BarackObama’s endorsement is a political kiss of death. \n\nPolitely decline next tim…"},{"created_at":"2018-11-08T23:59:49.000Z","id":"1060683341630861312","referenced_tweets":[{"type":"retweeted","id":"1060679482439335937"}],"author_id":"4802846372","entities":{"mentions":[{"start":3,"end":15,"username":"ChrisLoesch","id":"491461409"}]},"text":"RT @ChrisLoesch: Hey Scott, that headline is a lie. She was talking about how Trump handled the media during the election cycle. So unless…"},{"created_at":"2018-11-08T23:59:47.000Z","id":"1060683333770764289","referenced_tweets":[{"type":"retweeted","id":"1060574566282493952"}],"author_id":"823576508966940672","entities":{"mentions":[{"start":3,"end":10,"username":"McFaul","id":"454099919"}]},"text":"RT @McFaul: To those media outlets who covered extensively the \" the invading caravan\" before the election-- sometimes on page one -- but n…"},{"created_at":"2018-11-08T23:59:47.000Z","id":"1060683331526893568","referenced_tweets":[{"type":"retweeted","id":"1060574566282493952"}],"author_id":"2230571358","entities":{"mentions":[{"start":3,"end":10,"username":"McFaul","id":"454099919"}]},"text":"RT @McFaul: To those media outlets who covered extensively the \" the invading caravan\" before the election-- sometimes on page one -- but n…"}],"includes":{"users":[{"id":"33435305","name":"rebecca p","username":"rlp164"},{"id":"130496027","name":"Jon Favreau","username":"jonfavs"},{"id":"103643917","name":"Lauren Thomas","username":"BestRelaEver"},{"id":"454099919","name":"Michael McFaul","username":"McFaul"},{"id":"20117737","name":"Andrew Kotila","username":"Thefooze"},{"id":"266067803","name":"Infinite Idiocracy","username":"Infinite_Ennui"},{"id":"2353605901","name":"Ronna McDaniel","username":"GOPChairwoman"},{"id":"72854220","name":"anita nedley","username":"nita2293"},{"id":"7884802","name":"Anna Galland","username":"annagalland"},{"id":"2731618972","name":"The Shire\uD83C\uDDE8\uD83C\uDDE6","username":"vbrighthorses"},{"id":"68194357","name":"John Q. Barrett","username":"JohnQBarrett"},{"id":"1895972022","name":"Lewis","username":"tanktini"},{"id":"878247600096509952","name":"Candace Owens","username":"RealCandaceO"},{"id":"813286","name":"Barack Obama","username":"BarackObama"},{"id":"4802846372","name":"Greg Cole","username":"curbygc"},{"id":"491461409","name":"Chris Loesch","username":"ChrisLoesch"},{"id":"823576508966940672","name":"Jennifer Hanson\uD83D\uDC99\uD83D\uDDF3\uD83D\uDC99","username":"HansonJenL"},{"id":"2230571358","name":"Kerry Petter","username":"KerryPetter"}],"tweets":[{"created_at":"2018-11-08T21:29:10.000Z","id":"1060645426854977536","referenced_tweets":[{"type":"quoted","id":"1060596882970415106"}],"author_id":"130496027","text":"Accusing people who want every vote counted of stealing an election is disgusting. \n\nMarco’s really gone full Trump here. https://t.co/sNmVwyel4o"},{"created_at":"2018-11-08T16:47:35.000Z","id":"1060574566282493952","author_id":"454099919","text":"To those media outlets who covered extensively the \" the invading caravan\" before the election-- sometimes on page one -- but now have completely dropped reporting on this alleged national security threat, realize how badly Trump played you &amp; don't repeat."},{"created_at":"2018-11-08T23:40:57.000Z","id":"1060678592017977344","author_id":"2353605901","text":"#Broward Elections Supervisor Brenda Snipes is no stranger to destroying ballots and violating Florida election laws.\n \nSnipes has shown herself to be trouble. Voters in Florida should be paying attention!"},{"created_at":"2018-11-08T23:54:34.000Z","id":"1060682018705543175","referenced_tweets":[{"type":"quoted","id":"1060680669297340416"}],"author_id":"7884802","text":"These photos are gorgeous. In the wake of a massive wave election that put a real check on Trump's power, they are another reminder: We are the majority, and we're on the march to renew our democracy. #ProtectMueller \n\nhttps://t.co/eyYLd4wybi"},{"created_at":"2018-11-08T00:49:14.000Z","id":"1060333386454175746","referenced_tweets":[{"type":"replied_to","id":"1060333385376247810"}],"in_reply_to_user_id":"68194357","author_id":"68194357","entities":{"mentions":[{"start":141,"end":145,"username":"FBI","id":"17629860"},{"start":162,"end":168,"username":"Comey","id":"2334193741"}]},"text":"Whittaker then was practicing law in his own law firm in Des Moines (Whitaker Hagenow &amp; Gustoff LLP).  On CNN, he was critical of former @FBI  Director James @Comey, the FBI 2016 election-Trump campaign-Russia investigation, Mueller’s special counsel appointment, etc."},{"created_at":"2018-11-07T17:44:09.000Z","id":"1060226413754793984","author_id":"878247600096509952","entities":{"mentions":[{"start":37,"end":49,"username":"BarackObama","id":"813286"}]},"text":"What I learned this election cycle:\n\n@BarackObama’s endorsement is a political kiss of death. \n\nPolitely decline next time, political-hopefuls!\n\nAmericans views him as a bad salesman who has his strings pulled by globalists. \n\nTrump obliterated his legacy."},{"created_at":"2018-11-08T23:44:29.000Z","id":"1060679482439335937","author_id":"491461409","text":"Hey Scott, that headline is a lie. She was talking about how Trump handled the media during the election cycle. So unless you can produce some evidence of Trump physically assaulting a journalist then it’s obviously rhetorical.\nFull clip in context.  \nhttps://t.co/wUMtmrsgPs https://t.co/JUula6jOOd"}]},"meta":{"newest_id":"1060683380893769728","oldest_id":"1060683331526893568","result_count":10,"next_token":"b26v89c19zqg8o3fn0sk9crfxn81qbyqjsgqlxrifhawt"}}